{
  "120363421283478557@g.us": {
    "antibot": false,
    "antilink": false,
    "antistatus": false,
    "badword": false,
    "introcard": "",
    "outcrad": "",
    "notif": ""
  },
  "120363421522882896@g.us": {
    "antibot": false,
    "antilink": false,
    "antistatus": false,
    "badword": false,
    "introcard": "",
    "outcrad": "",
    "notif": ""
  },
  "6281370565843@s.whatsapp.net": {
    "antibot": false,
    "antilink": false,
    "antistatus": false,
    "badword": false,
    "introcard": "",
    "outcrad": "",
    "notif": ""
  },
  "120363399117932169@g.us": {
    "antibot": false,
    "antilink": false,
    "antistatus": false,
    "badword": false,
    "introcard": "",
    "outcrad": "",
    "notif": ""
  },
  "120363417815248032@g.us": {
    "antibot": false,
    "antilink": false,
    "antistatus": false,
    "badword": false,
    "introcard": "",
    "outcrad": "",
    "notif": ""
  },
  "6287814824142@s.whatsapp.net": {
    "antibot": false,
    "antilink": false,
    "antistatus": false,
    "badword": false,
    "introcard": "",
    "outcrad": "",
    "notif": ""
  },
  "120363422498020053@g.us": {
    "antibot": false,
    "antilink": false,
    "antistatus": false,
    "badword": false,
    "introcard": "",
    "outcrad": "",
    "notif": ""
  },
  "6285609341651@s.whatsapp.net": {
    "antibot": false,
    "antilink": false,
    "antistatus": false,
    "badword": false,
    "introcard": "",
    "outcrad": "",
    "notif": ""
  },
  "6282116833309-1631697825@g.us": {
    "antibot": false,
    "antilink": false,
    "antistatus": false,
    "badword": false,
    "introcard": "",
    "outcrad": "",
    "notif": ""
  },
  "120363400611037129@g.us": {
    "antibot": false,
    "antilink": false,
    "antistatus": false,
    "badword": false,
    "introcard": "",
    "outcrad": "",
    "notif": ""
  },
  "120363399122549716@g.us": {
    "antibot": false,
    "antilink": true,
    "antistatus": true,
    "badword": false,
    "introcard": "▀▄▀▄ ＩＮＴＲＯ ▄▀▄▀\\n\\n_*ＷＥＬＣＯＭＥ*_ \\n     *@grup*\\n        ☠️𝐒𝐄𝐊𝐓𝐎𝐑_𝐒𝐄𝐋𝐀𝐓𝐀𝐍☠️\\n\\n➢ɴᴀᴍᴀ?           =\\n\\n➢ᴜᴍᴜʀ?  =   \\n\\n➢ᴋᴇʟᴀs?  =\\n\\n➢ᴀsᴋᴏᴛ?  =\\n\\n➢ᴄᴇ/ᴄᴏ?  =\\n\\n➢sᴛᴀᴛᴜs?         =\\n\\n➢ᴛᴜᴊᴜᴀɴ ᴍᴀsᴜᴋ ɢʙ?  =\\n\\n\\n══✿══╡°˖✧✿✧˖°╞══✿══\\n• 𝘳𝘢𝘫𝘪𝘯\"𝘬𝘪 𝘯𝘪𝘮𝘣🙆🏻‍♀️\\n• 𝘣𝘢𝘯𝘵𝘶 𝘴𝘩𝘦𝘳\" 𝘭𝘪𝘯𝘬 𝘨𝘣🙆🏻‍♀️\\n• 𝘫𝘢𝘯𝘨𝘢𝘯𝘬𝘐 𝘭𝘶𝘱𝘢 𝘣𝘢𝘤𝘢 𝘥𝘦𝘴𝘬🙆🏻‍♀️\\nＢｅｔａｈｋｉ🫰🏻💋 @user\\n══✿══╡°˖✧✿✧˖°╞══✿══",
    "outcrad": "",
    "notif": false,
    "inviteCode": "DzyMc9y8hpU3zy3j1HBd8m"
  },
  "120363418062332572@g.us": {
    "antibot": false,
    "antilink": false,
    "antistatus": false,
    "badword": false,
    "introcard": "",
    "outcrad": "",
    "notif": ""
  },
  "6282116963782@s.whatsapp.net": {
    "antibot": false,
    "antilink": false,
    "antistatus": false,
    "badword": false,
    "introcard": "",
    "outcrad": "",
    "notif": ""
  },
  "120363404998766133@g.us": {
    "antibot": false,
    "antilink": true,
    "antistatus": false,
    "badword": false,
    "introcard": "selamat datang datang anak ayam",
    "outcrad": "",
    "notif": true,
    "inviteCode": "EqL1OZ0OzQaDi0F67H2uZ4"
  },
  "6282116833309@s.whatsapp.net": {
    "antibot": false,
    "antilink": false,
    "antistatus": false,
    "badword": false,
    "introcard": "",
    "outcrad": "",
    "notif": ""
  },
  "6287755505497@s.whatsapp.net": {
    "antibot": false,
    "antilink": false,
    "antistatus": false,
    "badword": false,
    "introcard": "",
    "outcrad": "",
    "notif": ""
  },
  "62882020404876@s.whatsapp.net": {
    "antibot": false,
    "antilink": false,
    "antistatus": false,
    "badword": false,
    "introcard": "",
    "outcrad": "",
    "notif": ""
  },
  "120363420260367591@newsletter": {
    "antibot": false,
    "antilink": false,
    "antistatus": false,
    "badword": false,
    "introcard": "",
    "outcrad": "",
    "notif": ""
  },
  "628979495267@s.whatsapp.net": {
    "antibot": false,
    "antilink": false,
    "antistatus": false,
    "badword": false,
    "introcard": "",
    "outcrad": "",
    "notif": ""
  },
  "120363294851860398@g.us": {
    "antibot": false,
    "antilink": false,
    "antistatus": false,
    "badword": false,
    "introcard": "",
    "outcrad": "",
    "notif": ""
  },
  "120363420414961562@newsletter": {
    "antibot": false,
    "antilink": false,
    "antistatus": false,
    "badword": false,
    "introcard": "",
    "outcrad": "",
    "notif": ""
  },
  "120363352582093674@newsletter": {
    "antibot": false,
    "antilink": false,
    "antistatus": false,
    "badword": false,
    "introcard": "",
    "outcrad": "",
    "notif": ""
  },
  "120363400098484740@g.us": {
    "antibot": false,
    "antilink": false,
    "antistatus": false,
    "badword": false,
    "introcard": "",
    "outcrad": "",
    "notif": ""
  },
  "62895323730413@s.whatsapp.net": {
    "antibot": false,
    "antilink": false,
    "antistatus": false,
    "badword": false,
    "introcard": "",
    "outcrad": "",
    "notif": ""
  },
  "6282184796053@s.whatsapp.net": {
    "antibot": false,
    "antilink": false,
    "antistatus": false,
    "badword": false,
    "introcard": "",
    "outcrad": "",
    "notif": ""
  },
  "6285824050029@s.whatsapp.net": {
    "antibot": false,
    "antilink": false,
    "antistatus": false,
    "badword": false,
    "introcard": "",
    "outcrad": "",
    "notif": ""
  },
  "6287731241002@s.whatsapp.net": {
    "antibot": false,
    "antilink": false,
    "antistatus": false,
    "badword": false,
    "introcard": "",
    "outcrad": "",
    "notif": ""
  },
  "6281515952397@s.whatsapp.net": {
    "antibot": false,
    "antilink": false,
    "antistatus": false,
    "badword": false,
    "introcard": "",
    "outcrad": "",
    "notif": ""
  },
  "6283853949028@s.whatsapp.net": {
    "antibot": false,
    "antilink": false,
    "antistatus": false,
    "badword": false,
    "introcard": "",
    "outcrad": "",
    "notif": ""
  },
  "6287816264055@s.whatsapp.net": {
    "antibot": false,
    "antilink": false,
    "antistatus": false,
    "badword": false,
    "introcard": "",
    "outcrad": "",
    "notif": ""
  },
  "6285857735057@s.whatsapp.net": {
    "antibot": false,
    "antilink": false,
    "antistatus": false,
    "badword": false,
    "introcard": "",
    "outcrad": "",
    "notif": ""
  },
  "6283829566363@s.whatsapp.net": {
    "antibot": false,
    "antilink": false,
    "antistatus": false,
    "badword": false,
    "introcard": "",
    "outcrad": "",
    "notif": ""
  },
  "6287894991151@s.whatsapp.net": {
    "antibot": false,
    "antilink": false,
    "antistatus": false,
    "badword": false,
    "introcard": "",
    "outcrad": "",
    "notif": ""
  },
  "6282396587515@s.whatsapp.net": {
    "antibot": false,
    "antilink": false,
    "antistatus": false,
    "badword": false,
    "introcard": "",
    "outcrad": "",
    "notif": ""
  },
  "120363421694828190@g.us": {
    "antibot": false,
    "antilink": false,
    "antistatus": false,
    "badword": false,
    "introcard": "",
    "outcrad": "",
    "notif": ""
  },
  "6287864590512@s.whatsapp.net": {
    "antibot": false,
    "antilink": false,
    "antistatus": false,
    "badword": false,
    "introcard": "",
    "outcrad": "",
    "notif": ""
  },
  "62881022387633@s.whatsapp.net": {
    "antibot": false,
    "antilink": false,
    "antistatus": false,
    "badword": false,
    "introcard": "",
    "outcrad": "",
    "notif": ""
  },
  "6285783583542@s.whatsapp.net": {
    "antibot": false,
    "antilink": false,
    "antistatus": false,
    "badword": false,
    "introcard": "",
    "outcrad": "",
    "notif": ""
  },
  "6285704023069@s.whatsapp.net": {
    "antibot": false,
    "antilink": false,
    "antistatus": false,
    "badword": false,
    "introcard": "",
    "outcrad": "",
    "notif": ""
  },
  "120363420161139855@g.us": {
    "antibot": false,
    "antilink": true,
    "antistatus": false,
    "badword": false,
    "introcard": "",
    "outcrad": "",
    "notif": true,
    "inviteCode": "EZaO61WHma67GYP5Y7LxYZ"
  },
  "120363419310709174@g.us": {
    "antibot": false,
    "antilink": false,
    "antistatus": false,
    "badword": false,
    "introcard": "",
    "outcrad": "",
    "notif": ""
  },
  "120363401148757069@g.us": {
    "antibot": false,
    "antilink": false,
    "antistatus": false,
    "badword": false,
    "introcard": "",
    "outcrad": "",
    "notif": ""
  },
  "6282195548119@s.whatsapp.net": {
    "antibot": false,
    "antilink": false,
    "antistatus": false,
    "badword": false,
    "introcard": "",
    "outcrad": "",
    "notif": ""
  },
  "6281344195326@s.whatsapp.net": {
    "antibot": false,
    "antilink": false,
    "antistatus": false,
    "badword": false,
    "introcard": "",
    "outcrad": "",
    "notif": ""
  },
  "6282297396583@s.whatsapp.net": {
    "antibot": false,
    "antilink": false,
    "antistatus": false,
    "badword": false,
    "introcard": "",
    "outcrad": "",
    "notif": ""
  },
  "31001694707930@lid": {
    "antibot": false,
    "antilink": false,
    "antistatus": false,
    "badword": false,
    "introcard": "",
    "outcrad": "",
    "notif": ""
  },
  "120363020281876253@g.us": {
    "antibot": false,
    "antilink": false,
    "antistatus": false,
    "badword": false,
    "introcard": "",
    "outcrad": "",
    "notif": ""
  },
  "120363422661502447@g.us": {
    "antibot": false,
    "antilink": false,
    "antistatus": false,
    "badword": false,
    "introcard": "",
    "outcrad": "",
    "notif": ""
  },
  "120363333927458443@g.us": {
    "antibot": false,
    "antilink": false,
    "antistatus": false,
    "badword": false,
    "introcard": "",
    "outcrad": "",
    "notif": ""
  },
  "40961405145334@lid": {
    "antibot": false,
    "antilink": false,
    "antistatus": false,
    "badword": false,
    "introcard": "",
    "outcrad": "",
    "notif": ""
  },
  "120363422698111853@g.us": {
    "antibot": false,
    "antilink": false,
    "antistatus": false,
    "badword": false,
    "introcard": "",
    "outcrad": "",
    "notif": ""
  },
  "98321163149341@lid": {
    "antibot": false,
    "antilink": false,
    "antistatus": false,
    "badword": false,
    "introcard": "",
    "outcrad": "",
    "notif": ""
  },
  "34140963512434@lid": {
    "antibot": false,
    "antilink": false,
    "antistatus": false,
    "badword": false,
    "introcard": "",
    "outcrad": "",
    "notif": ""
  },
  "271274479751327@lid": {
    "antibot": false,
    "antilink": false,
    "antistatus": false,
    "badword": false,
    "introcard": "",
    "outcrad": "",
    "notif": ""
  },
  "120363401955728351@g.us": {
    "antibot": false,
    "antilink": false,
    "antistatus": false,
    "badword": false,
    "introcard": "",
    "outcrad": "",
    "notif": ""
  },
  "219743898337438@lid": {
    "antibot": false,
    "antilink": false,
    "antistatus": false,
    "badword": false,
    "introcard": "",
    "outcrad": "",
    "notif": ""
  },
  "120363345318229606@newsletter": {
    "antibot": false,
    "antilink": false,
    "antistatus": false,
    "badword": false,
    "introcard": "",
    "outcrad": "",
    "notif": ""
  },
  "165124899909637@lid": {
    "antibot": false,
    "antilink": false,
    "antistatus": false,
    "badword": false,
    "introcard": "",
    "outcrad": "",
    "notif": ""
  },
  "37340512833705@lid": {
    "antibot": false,
    "antilink": false,
    "antistatus": false,
    "badword": false,
    "introcard": "",
    "outcrad": "",
    "notif": ""
  },
  "120363307916718837@g.us": {
    "antibot": false,
    "antilink": false,
    "antistatus": false,
    "badword": false,
    "introcard": "",
    "outcrad": "",
    "notif": ""
  },
  "243082767376547@lid": {
    "antibot": false,
    "antilink": false,
    "antistatus": false,
    "badword": false,
    "introcard": "",
    "outcrad": "",
    "notif": ""
  },
  "37331855786090@lid": {
    "antibot": false,
    "antilink": false,
    "antistatus": false,
    "badword": false,
    "introcard": "",
    "outcrad": "",
    "notif": ""
  },
  "628170110808@s.whatsapp.net": {
    "antibot": false,
    "antilink": false,
    "antistatus": false,
    "badword": false,
    "introcard": "",
    "outcrad": "",
    "notif": ""
  },
  "120363214644878452@g.us": {
    "antibot": false,
    "antilink": false,
    "antistatus": false,
    "badword": false,
    "introcard": "",
    "outcrad": "",
    "notif": ""
  },
  "127647048855688@lid": {
    "antibot": false,
    "antilink": false,
    "antistatus": false,
    "badword": false,
    "introcard": "",
    "outcrad": "",
    "notif": ""
  },
  "16969986232396@lid": {
    "antibot": false,
    "antilink": false,
    "antistatus": false,
    "badword": false,
    "introcard": "",
    "outcrad": "",
    "notif": ""
  },
  "1194521038945@lid": {
    "antibot": false,
    "antilink": false,
    "antistatus": false,
    "badword": false,
    "introcard": "",
    "outcrad": "",
    "notif": ""
  },
  "62818880876@s.whatsapp.net": {
    "antibot": false,
    "antilink": false,
    "antistatus": false,
    "badword": false,
    "introcard": "",
    "outcrad": "",
    "notif": ""
  },
  "58412159205480@lid": {
    "antibot": false,
    "antilink": false,
    "antistatus": false,
    "badword": false,
    "introcard": "",
    "outcrad": "",
    "notif": ""
  },
  "170407172776077@lid": {
    "antibot": false,
    "antilink": false,
    "antistatus": false,
    "badword": false,
    "introcard": "",
    "outcrad": "",
    "notif": ""
  },
  "120363405823102753@g.us": {
    "antibot": false,
    "antilink": false,
    "antistatus": false,
    "badword": false,
    "introcard": "",
    "outcrad": "",
    "notif": ""
  },
  "173865242222663@lid": {
    "antibot": false,
    "antilink": false,
    "antistatus": false,
    "badword": false,
    "introcard": "",
    "outcrad": "",
    "notif": ""
  },
  "95877041496118@lid": {
    "antibot": false,
    "antilink": false,
    "antistatus": false,
    "badword": false,
    "introcard": "",
    "outcrad": "",
    "notif": ""
  },
  "275149110702262@lid": {
    "antibot": false,
    "antilink": false,
    "antistatus": false,
    "badword": false,
    "introcard": "",
    "outcrad": "",
    "notif": ""
  },
  "79148278136936@lid": {
    "antibot": false,
    "antilink": false,
    "antistatus": false,
    "badword": false,
    "introcard": "",
    "outcrad": "",
    "notif": ""
  },
  "151968928530687@lid": {
    "antibot": false,
    "antilink": false,
    "antistatus": false,
    "badword": false,
    "introcard": "",
    "outcrad": "",
    "notif": ""
  },
  "98767621648496@lid": {
    "antibot": false,
    "antilink": false,
    "antistatus": false,
    "badword": false,
    "introcard": "",
    "outcrad": "",
    "notif": ""
  },
  "120363390652551239@g.us": {
    "antibot": false,
    "antilink": false,
    "antistatus": false,
    "badword": false,
    "introcard": "",
    "outcrad": "",
    "notif": ""
  },
  "120363425353797354@g.us": {
    "antibot": false,
    "antilink": false,
    "antistatus": false,
    "badword": false,
    "introcard": "",
    "outcrad": "",
    "notif": ""
  },
  "120363424622880213@g.us": {
    "antibot": false,
    "antilink": false,
    "antistatus": false,
    "badword": false,
    "introcard": "",
    "outcrad": "",
    "notif": ""
  },
  "120363406236098430@g.us": {
    "antibot": false,
    "antilink": false,
    "antistatus": false,
    "badword": false,
    "introcard": "",
    "outcrad": "",
    "notif": ""
  },
  "106155099599035@lid": {
    "antibot": false,
    "antilink": false,
    "antistatus": false,
    "badword": false,
    "introcard": "",
    "outcrad": "",
    "notif": ""
  },
  "120363402145232822@g.us": {
    "antibot": false,
    "antilink": false,
    "antistatus": false,
    "badword": false,
    "introcard": "",
    "outcrad": "",
    "notif": ""
  },
  "184370497355839@lid": {
    "antibot": false,
    "antilink": false,
    "antistatus": false,
    "badword": false,
    "introcard": "",
    "outcrad": "",
    "notif": ""
  },
  "120363427457065908@g.us": {
    "antibot": false,
    "antilink": true,
    "antistatus": false,
    "badword": false,
    "introcard": "🤭 *WELCOME TO @group DASAR @user KACUNG*\\n┃\\n┣ 👤nama : \\n┃ ➜ \\n┃\\n┣ .🏛️kelas :\\n┃ ➜ \\n┃\\n┣ 📍 asal : \\n┃ ➜ \\n┃\\n┣ 📇umur :\\n┃ ➜ \\n┃\\n┣ 📇gender :\\n┃ ➜ \\n┃\\n╰──────────────⬣",
    "outcrad": "",
    "notif": true,
    "inviteCode": "LcYWqxIwGPbKODwY0XXR1w",
    "allowImage": false,
    "outcard": "😘*Hati Hati di jalan ya DASAR  KACUNG*\\n┃\\n┣ 👤nama : \\n┃ ➜ @user\\n┃\\n┣ 🚪 keluar :\\n┃ ➜ dari @group\\n┃\\n┣ 🗓️ tanggal :\\n┃ ➜ @tanggal\\n╰──────────────⬣"
  },
  "145471196639437@lid": {
    "antibot": false,
    "antilink": false,
    "antistatus": false,
    "badword": false,
    "introcard": "",
    "outcrad": "",
    "notif": ""
  },
  "109960373489665@lid": {
    "antibot": false,
    "antilink": false,
    "antistatus": false,
    "badword": false,
    "introcard": "",
    "outcrad": "",
    "notif": ""
  },
  "120363423288739809@g.us": {
    "antibot": false,
    "antilink": false,
    "antistatus": false,
    "badword": false,
    "introcard": "",
    "outcrad": "",
    "notif": ""
  },
  "82807657361571@lid": {
    "antibot": false,
    "antilink": false,
    "antistatus": false,
    "badword": false,
    "introcard": "",
    "outcrad": "",
    "notif": ""
  },
  "75553222701199@lid": {
    "antibot": false,
    "antilink": false,
    "antistatus": false,
    "badword": false,
    "introcard": "",
    "outcrad": "",
    "notif": ""
  },
  "120363408543448933@g.us": {
    "antibot": false,
    "antilink": false,
    "antistatus": false,
    "badword": false,
    "introcard": "♠``` ```welcome @user to the @group \\nselamat datang di grup`````` ♠\\n\\n~~°♠👻 _INTRO_👻♠°~~\\n\\n~^♠NAMA♠^~:\\n\\n~^♠KELAS♠^~:\\n\\n~^♠UMUR♠^~:\\n\\n~^♠GENDER♠^~:\\n\\n~^♠STATUS ♠^~:\\n\\n~^♠HOBI♠^~:\\n\\n*👻 ~_s a l k e n  s e m u a  s e m o g a  b e t a h  y a_~ 👻*\\n\\n *🎼🎼 *wajib intro ya🎼🎼**",
    "outcrad": "",
    "notif": true,
    "allowImage": false
  },
  "120363408865077388@g.us": {
    "antibot": true,
    "antilink": false,
    "antistatus": true,
    "badword": true,
    "introcard": "! setintrocard anak ayam",
    "outcrad": "",
    "notif": true,
    "warnings": {
      "98321163149341@lid": 1
    },
    "showGroupPic": false,
    "allowImage": false
  },
  "172872953790661@lid": {
    "antibot": false,
    "antilink": false,
    "antistatus": false,
    "badword": false,
    "introcard": "",
    "outcrad": "",
    "notif": ""
  },
  "61856739774650@lid": {
    "antibot": false,
    "antilink": false,
    "antistatus": false,
    "badword": false,
    "introcard": "",
    "outcrad": "",
    "notif": ""
  },
  "177622734630976@lid": {
    "antibot": false,
    "antilink": false,
    "antistatus": false,
    "badword": false,
    "introcard": "",
    "outcrad": "",
    "notif": ""
  },
  "167341237219485@lid": {
    "antibot": false,
    "antilink": false,
    "antistatus": false,
    "badword": false,
    "introcard": "",
    "outcrad": "",
    "notif": ""
  },
  "148249973383223@lid": {
    "antibot": false,
    "antilink": false,
    "antistatus": false,
    "badword": false,
    "introcard": "",
    "outcrad": "",
    "notif": ""
  },
  "130078050656384@lid": {
    "antibot": false,
    "antilink": false,
    "antistatus": false,
    "badword": false,
    "introcard": "",
    "outcrad": "",
    "notif": ""
  },
  "107971753340977@lid": {
    "antibot": false,
    "antilink": false,
    "antistatus": false,
    "badword": false,
    "introcard": "",
    "outcrad": "",
    "notif": ""
  },
  "190641367715949@lid": {
    "antibot": false,
    "antilink": false,
    "antistatus": false,
    "badword": false,
    "introcard": "",
    "outcrad": "",
    "notif": ""
  },
  "244860984504527@lid": {
    "antibot": false,
    "antilink": false,
    "antistatus": false,
    "badword": false,
    "introcard": "",
    "outcrad": "",
    "notif": ""
  },
  "267392248746113@lid": {
    "antibot": false,
    "antilink": false,
    "antistatus": false,
    "badword": false,
    "introcard": "",
    "outcrad": "",
    "notif": ""
  },
  "120363424520970458@g.us": {
    "antibot": false,
    "antilink": false,
    "antistatus": false,
    "badword": false,
    "introcard": "",
    "outcrad": "",
    "notif": ""
  },
  "209586283897084@lid": {
    "antibot": false,
    "antilink": false,
    "antistatus": false,
    "badword": false,
    "introcard": "",
    "outcrad": "",
    "notif": ""
  },
  "135218992267310@lid": {
    "antibot": false,
    "antilink": false,
    "antistatus": false,
    "badword": false,
    "introcard": "",
    "outcrad": "",
    "notif": ""
  },
  "120363403351541203@g.us": {
    "antibot": false,
    "antilink": false,
    "antistatus": false,
    "badword": false,
    "introcard": "",
    "outcrad": "",
    "notif": ""
  },
  "233856892449009@lid": {
    "antibot": false,
    "antilink": false,
    "antistatus": false,
    "badword": false,
    "introcard": "",
    "outcrad": "",
    "notif": ""
  },
  "83876735152331@lid": {
    "antibot": false,
    "antilink": false,
    "antistatus": false,
    "badword": false,
    "introcard": "",
    "outcrad": "",
    "notif": ""
  },
  "111321911660587@lid": {
    "antibot": false,
    "antilink": false,
    "antistatus": false,
    "badword": false,
    "introcard": "",
    "outcrad": "",
    "notif": ""
  },
  "192294410027254@lid": {
    "antibot": false,
    "antilink": false,
    "antistatus": false,
    "badword": false,
    "introcard": "",
    "outcrad": "",
    "notif": ""
  },
  "238396991643801@lid": {
    "antibot": false,
    "antilink": false,
    "antistatus": false,
    "badword": false,
    "introcard": "",
    "outcrad": "",
    "notif": ""
  },
  "2521733050552@lid": {
    "antibot": false,
    "antilink": false,
    "antistatus": false,
    "badword": false,
    "introcard": "",
    "outcrad": "",
    "notif": ""
  },
  "120363424718542524@g.us": {
    "antibot": false,
    "antilink": false,
    "antistatus": false,
    "badword": false,
    "introcard": "🤭 *WELCOME TO @group DASAR @user KACUNG*\\n┃\\n┣ 👤nama : \\n┃ ➜ \\n┃\\n┣ 🏛️kelas :\\n┃ ➜ \\n┃\\n┣ 📍 asal : \\n┃ ➜ \\n┃\\n┣ 📇umur :\\n┃ ➜ \\n┃\\n┣ 📇gender :\\n┃ ➜ \\n┃\\n╰──────────────⬣",
    "outcrad": "",
    "notif": true,
    "allowImage": false
  },
  "71971370987571@lid": {
    "antibot": false,
    "antilink": false,
    "antistatus": false,
    "badword": false,
    "introcard": "",
    "outcrad": "",
    "notif": ""
  },
  "122385764217081@lid": {
    "antibot": false,
    "antilink": false,
    "antistatus": false,
    "badword": false,
    "introcard": "",
    "outcrad": "",
    "notif": ""
  },
  "38238697840754@lid": {
    "antibot": false,
    "antilink": false,
    "antistatus": false,
    "badword": false,
    "introcard": "",
    "outcrad": "",
    "notif": ""
  },
  "14367135412410@lid": {
    "antibot": false,
    "antilink": false,
    "antistatus": false,
    "badword": false,
    "introcard": "",
    "outcrad": "",
    "notif": ""
  },
  "120363404824598444@g.us": {
    "antibot": true,
    "antilink": true,
    "antistatus": false,
    "badword": false,
    "introcard": "WELCOME @user TO GRUP @group\\n\\n💞 KARTU INTRO 💞\\n🎀NAMA\\n🎀KELAS\\n🎀 UMUR \\n🎀 AGAMA \\n🎀ASAL\\n🌷 SALKEN MEMBER BARU 🌷",
    "outcrad": "",
    "notif": true,
    "inviteCode": "DYbRQGukj0H87HUhJnx5N7",
    "allowImage": false
  },
  "120363427392694100@g.us": {
    "antibot": false,
    "antilink": false,
    "antistatus": false,
    "badword": false,
    "introcard": "*WELLCOME @user*\\n❃𝐊𝐀𝐑𝐓𝐔 𝐈𝐍𝐓𝐑𝐎 ❃\\n❃𝐍𝐀𝐌𝐀\\n❃𝐊𝐄𝐋𝐀𝐒\\n❃𝐔𝐌𝐔𝐑\\n❃𝐀𝐆𝐀𝐌𝐀\\n❃𝐀𝐒𝐀𝐋𝐋\\n★𝐒𝐀𝐋𝐊𝐄𝐍 𝐘𝐀𝐍𝐆 𝐁𝐀𝐑𝐔 𝐁𝐄𝐑𝐆𝐀𝐁𝐔𝐍𝐆 𝐒𝐄𝐌𝐎𝐆𝐀 𝐁𝐄𝐓𝐀𝐇𝐇𝐇 𝐘𝐀𝐇𝐇𝐇𝐇𝐇 𝐃𝐈 𝐆𝐑𝐔𝐏𝐏 𝐈𝐍𝐈𝐇𝐇𝐇𝐇 𝐏𝐄𝐒𝐀𝐍𝐍𝐍 𝐃𝐀𝐑𝐈𝐈𝐈𝐈 𝐂𝐀𝐇𝐂𝐀𝐀",
    "outcrad": "",
    "notif": true
  },
  "186887616630863@lid": {
    "antibot": false,
    "antilink": false,
    "antistatus": false,
    "badword": false,
    "introcard": "",
    "outcrad": "",
    "notif": ""
  },
  "120363422221274355@newsletter": {
    "antibot": false,
    "antilink": false,
    "antistatus": false,
    "badword": false,
    "introcard": "",
    "outcrad": "",
    "notif": ""
  },
  "106704872198311@lid": {
    "antibot": false,
    "antilink": false,
    "antistatus": false,
    "badword": false,
    "introcard": "",
    "outcrad": "",
    "notif": ""
  },
  "177417129836561@lid": {
    "antibot": false,
    "antilink": false,
    "antistatus": false,
    "badword": false,
    "introcard": "",
    "outcrad": "",
    "notif": ""
  },
  "49096257761288@lid": {
    "antibot": false,
    "antilink": false,
    "antistatus": false,
    "badword": false,
    "introcard": "",
    "outcrad": "",
    "notif": ""
  },
  "120363334732957782@newsletter": {
    "antibot": false,
    "antilink": false,
    "antistatus": false,
    "badword": false,
    "introcard": "",
    "outcrad": "",
    "notif": ""
  }
}